AHB_SLV/answer/sim/testcase.v

	//write mode reg
	#10;
        $display("write mode reg ....\n");
	ahb_write(32'h04,32'h01);
	#10;
	//write opcode_a reg
        $display("write opcode_a reg ....\n");
	ahb_write(32'h08,32'h0000_3254);
	#10;
	//write opcode_b reg
        $display("write opcode_b reg ....\n");
	ahb_write(32'h0C,32'h0000_ffff);
	#10;
	//write ctrl reg
        $display("write ctrl reg ....\n");
	ahb_write(32'h00,32'h01);
	
	#10;
	//read result reg
        $display("read result reg ....\n");
	ahb_read(32'h10,rdata);
        $display("The result is %h\n",rdata);
        
        if(rdata == 32'h0000ffff)
        $display("TC_or case_passed ^_^\n");
        else
        $display("TC_or case_failed *_*\n");

AHB_SLV/old_answer/rtl/clac.v
module clac(
          ctrl,
          clac_mode,
          opcode_a,
          opcode_b,
          result
);

input ctrl;
input [1:0] clac_mode;
input [15:0] opcode_a;
input [15:0] opcode_b;

output [31:0] result;
reg    [31:0] result;

always@(*)
begin
  if(ctrl)
  case(clac_mode)
  2'b00: result = opcode_a & opcode_b;
  2'b01: result = opcode_a | opcode_b;
  2'b10: result = opcode_a ^ opcode_b;
  2'b11: result = opcode_a + opcode_b;
  endcase
  else
  result = 32'b0;
end

endmodule

AHB_SLV/old_answer/rtl/ahb_slave.v

module ahb_slave_clac(
            //input signals
            hclk,
		        hresetn,
		        hsel,
		        hwrite,
            hready,
		        hsize,
		        htrans,
		        hburst,
		        hwdata,
		        haddr,
                        
            result,
            //output signals
		        hready_resp,
		        hresp,
		        hrdata,
            ctrl,
            clac_mode,
            opcode_a,
            opcode_b
                   );
  input          hclk;
  input          hresetn;
  input          hsel;
  input          hwrite;
  input          hready;
  input [2:0]    hsize ;    
  input [2:0]    hburst;
  input [1:0]    htrans;
  input [31:0]   hwdata;
  input [7:0]    haddr;
  
  input [31:0]   result;

  output         hready_resp;
  output [1:0]   hresp;
  output [31:0]  hrdata;
  output         ctrl;
  output [1:0]   clac_mode;
  output [15:0]  opcode_a;
  output [15:0]  opcode_b;

  reg    [31:0] hrdata;

  reg hwrite_r      ;
  reg [2:0] hsize_r ;    
  reg [2:0] hburst_r;
  reg [1:0] htrans_r;
  reg [7:0] haddr_r;


  wire    ahb_write;
  wire    ahb_read;
  
  reg  enable_r;
  reg [1:0] ctrl_r;
  reg [15:0] opa_r;
  reg [15:0] opb_r;

  parameter     IDLE   = 2'b00,
                BUSY   = 2'b01,
		NONSEQ = 2'b10,
		SEQ    = 2'b11;

 
  parameter     ENABLE_ADDR = 8'h00,
                CTRL_ADDR   = 8'h04,
                OPA_ADDR    = 8'h08,
                OPB_ADDR    = 8'h0c,
                RESULT_ADDR = 8'h10;

  assign ctrl = enable_r;
  assign clac_mode = ctrl_r;
  assign opcode_a = opa_r; 
  assign opcode_b = opb_r; 

  assign hready_resp = 1'b1;
  assign hresp  = 2'b00;
  
  // generate write and read enable signal
  assign ahb_write = ((htrans_r == NONSEQ) || (htrans_r == SEQ)) && hwrite_r && hready;
  assign ahb_read =  ((htrans_r == NONSEQ) || (htrans_r == SEQ)) && (!hwrite_r) && hready;


  always @(posedge hclk or negedge hresetn )
  begin
    if(!hresetn)
    begin
      enable_r <= 1'b0;    
      ctrl_r   <= 2'b0;
      opa_r    <= 16'b0;
      opb_r    <= 16'b0;
    end
    else if(ahb_write)
    begin
      case(haddr_r)
      ENABLE_ADDR: enable_r <= hwdata[0]; 
      CTRL_ADDR  : ctrl_r   <= hwdata[1:0]; 
      OPA_ADDR   : opa_r    <= hwdata[15:0]; 
      OPB_ADDR   : opb_r    <= hwdata[15:0]; 
      endcase
    end
  end
  
  //--------------------------------------------------------
  //  Sequential portion
  //--------------------------------------------------------

  //tmp the ahb address and control signals
  always@(posedge hclk or negedge hresetn)
  begin
    if(!hresetn) 
    begin
      hwrite_r  <= 1'b0  ;
      hsize_r   <= 3'b0  ;    
      hburst_r  <= 3'b0  ;
      htrans_r  <= 2'b0  ;
      haddr_r   <= 8'b0 ;
    end
    else         
    if(hready && hsel)
    begin
      hwrite_r  <= hwrite ;
      hsize_r   <= hsize  ;    
      hburst_r  <= hburst ;
      htrans_r  <= htrans ;
      haddr_r   <= haddr  ;
    end
   else
    begin
      hwrite_r  <= 1'b0 ;
      hsize_r   <= 3'b0 ;    
      hburst_r  <= 3'b0 ;
      htrans_r  <= 2'b0 ;
    end
  end

  //assign hrdata = ahb_read ? bogus_reg : 32'h0;
  always@(*)
  begin
    if(ahb_read)
    begin
    case(haddr_r[7:0])
      ENABLE_ADDR      :  hrdata = {31'b0,enable_r}; 
      CTRL_ADDR        :  hrdata = {30'b0,ctrl_r}; 
      OPA_ADDR         :  hrdata = {16'b0,opa_r}; 
      OPB_ADDR         :  hrdata = {16'b0,opb_r}; 
      RESULT_ADDR      :  hrdata = result; 
      default          :  hrdata = 32'h0; 
    endcase
    end
    else
      hrdata = 32'b0;
  end


endmodule

AHB_SLV/answer/rtl/ahb_clac_top.v

module ahb_clac_top(
                        //input signals
                        hclk,
		        hresetn,
		        hsel,
		        hwrite,
                        hready,
		        hsize,
		        htrans,
		        hburst,
		        hwdata,
		        haddr,
                        
                        //output signals
		        hready_resp,
		        hresp,
		        hrdata
                   );
  input hclk;
  input hresetn;
  input hsel;
  input hwrite;
  input hready;
  input [2:0] hsize ;    
  input [2:0] hburst;
  input [1:0] htrans;
  input [31:0] hwdata;
  input [7:0] haddr;
  

  output hready_resp;
  output [1:0] hresp;
  output [31:0] hrdata;

  wire  ctrl;
  wire  [1:0] clac_mode;
  wire  [15:0] opcode_a;
  wire  [15:0] opcode_b;
  wire  [31:0] result;



ahb_slave_clac U_slave_if(
                        .hclk        (hclk        ),
		        .hresetn     (hresetn     ),
		        .hsel        (hsel        ),
		        .hwrite      (hwrite      ),
                        .hready      (hready      ),
		        .hsize       (hsize       ),
		        .htrans      (htrans      ),
		        .hburst      (hburst      ),
		        .hwdata      (hwdata      ),
		        .haddr       (haddr       ),
                        .result      (result      ),
		        .hready_resp (hready_resp ),
		        .hresp       (hresp       ),
		        .hrdata      (hrdata      ),
                        .ctrl        (ctrl        ),
                        .clac_mode   (clac_mode   ),
                        .opcode_a    (opcode_a    ),
                        .opcode_b    (opcode_b    )
                       ); 


clac U_clac(
          .ctrl      (ctrl     ),
          .clac_mode (clac_mode),
          .opcode_a  (opcode_a ),
          .opcode_b  (opcode_b ),
          .result    (result   )
         );

endmodule

AHB_SLV/old_answer/tb/ahb_clac_tb_2.v




//`timescale 1ns/1ps

module ahb_clac_top_tb;

reg		hclk;
reg    		hresetn;
reg    		hsel;
reg   	 	hwrite;
reg		hready;
reg [2:0]  	hsize ;    
reg [2:0]  	hburst;
reg [1:0]  	htrans;
reg [31:0] 	hwdata;
reg [31:0] 	haddr;		

wire         hready_resp;
wire [1:0]   hresp;
wire [31:0]  hrdata;

reg [31:0] rdata;

// clock generator
initial 
begin
	hclk = 0;
	forever
	begin
		#10 hclk = ~hclk;
	end
end

//dump waveform 
`ifdef VPD_ON
initial begin
  $vcdpluson();
end
`endif

`ifdef FSDB_ON
initial begin
  $fsdbDumpfile("aaa.fsdb");
  $fsdbDumpvars();
end
`endif

`ifdef VCD_ON
initial begin
  $dumpfile("aaa.vcd");
  $dumpvars();
end
`endif

`ifdef SHM_ON
initial  begin
  $shm_open("aaa.shm");
  $shm_probe(ahb_clac_top_tb,"AC");
  $shm_close;
end
`endif

parameter     IDLE   = 2'b00,
              BUSY   = 2'b01,
	      NONSEQ = 2'b10,
	      SEQ    = 2'b11;
 
initial begin
	hresetn = 0;
	htrans = IDLE;
	hsize = 3'b00;
	hburst=3'b00;
	hwrite = 0;
	hsel = 0;
	hready = 0;
	haddr = 0;
	#200;
	hresetn = 1;
  $display("sim start....\n\n\n");	
`include "testcase.v"


 
	#100;
	$finish;
end



ahb_clac_top U_clac_top(
                        .hclk         (hclk       ),
		        .hresetn      (hresetn    ),
		        .hsel         (hsel       ),
		        .hwrite       (hwrite     ),
                        .hready       (hready     ),
		        .hsize        (hsize      ),
		        .htrans       (htrans     ),
		        .hburst       (hburst     ),
		        .hwdata       (hwdata     ),
		        .haddr        (haddr      ),
		        .hready_resp  (hready_resp),
		        .hresp        (hresp      ),
		        .hrdata       (hrdata     )
                   );

	
task ahb_write(input [31:0] addr,input [31:0] wdata);
begin
	@(posedge hclk);
  #1;
	hsize  = 3'b10;
  htrans = NONSEQ;
  hwrite = 1;
	hsel = 1;
	hready = 1;
	haddr = addr;
	@(posedge hclk);
  #1;
	hsize  = 2'b00;
  htrans = IDLE;
  hwrite = 0;
	hsel = 0;
	hwdata = wdata;
	@(posedge hclk);
  #1;
	haddr = 32'b0;
	@(posedge hclk);
end
endtask

task ahb_read(input [31:0] addr,output [31:0] rdata);
begin
	@(posedge hclk);
        #1;
	haddr = addr;
	hsize  = 2'b10;
        htrans = NONSEQ;
        hwrite = 0;
	hsel = 1;
	@(posedge hclk);
        #1;
	hsize  = 2'b00;
        htrans = IDLE;
        hwrite = 0;
	hsel = 0;
	@(posedge hclk);
        rdata = hrdata; 
	haddr = 32'b0;
	@(posedge hclk);
end
endtask

endmodule

AHB_SLV/old_answer/sim_vcs/aaa.vcd
$date
	Mon Jul 16 22:35:39 2018
$end

$version
	Synopsys VCS version G-2012.09
$end

$timescale
	1ps
$end

$comment Csum: 1 ae1349ca65ac37bc $end


$scope module ahb_clac_top_tb $end
$var reg 1 ! hclk $end
$var reg 1 " hresetn $end
$var reg 1 # hsel $end
$var reg 1 $ hwrite $end
$var reg 1 % hready $end
$var reg 3 & hsize [2:0] $end
$var reg 3 ' hburst [2:0] $end
$var reg 2 ( htrans [1:0] $end
$var reg 32 ) hwdata [31:0] $end
$var reg 32 * haddr [31:0] $end
$var wire 1 + hready_resp $end
$var wire 2 , hresp [1:0] $end
$var wire 32 - hrdata [31:0] $end
$var reg 32 . rdata [31:0] $end

$scope task ahb_write $end
$var reg 32 / addr [31:0] $end
$var reg 32 0 wdata [31:0] $end
$upscope $end


$scope task ahb_read $end
$var reg 32 1 addr [31:0] $end
$var reg 32 2 rdata [31:0] $end
$upscope $end


$scope module U_clac_top $end
$var wire 1 ! hclk $end
$var wire 1 " hresetn $end
$var wire 1 # hsel $end
$var wire 1 $ hwrite $end
$var wire 1 % hready $end
$var wire 3 & hsize [2:0] $end
$var wire 3 ' hburst [2:0] $end
$var wire 2 ( htrans [1:0] $end
$var wire 32 ) hwdata [31:0] $end
$var wire 8 3 haddr [7:0] $end
$var wire 1 + hready_resp $end
$var wire 2 , hresp [1:0] $end
$var wire 32 - hrdata [31:0] $end
$var wire 1 4 ctrl $end
$var wire 2 5 clac_mode [1:0] $end
$var wire 16 6 opcode_a [15:0] $end
$var wire 16 7 opcode_b [15:0] $end
$var wire 32 8 result [31:0] $end

$scope module U_slave_if $end
$var wire 1 ! hclk $end
$var wire 1 " hresetn $end
$var wire 1 # hsel $end
$var wire 1 $ hwrite $end
$var wire 1 % hready $end
$var wire 3 & hsize [2:0] $end
$var wire 3 ' hburst [2:0] $end
$var wire 2 ( htrans [1:0] $end
$var wire 32 ) hwdata [31:0] $end
$var wire 8 3 haddr [7:0] $end
$var wire 32 8 result [31:0] $end
$var wire 1 + hready_resp $end
$var wire 2 , hresp [1:0] $end
$var reg 32 9 hrdata [31:0] $end
$var wire 1 4 ctrl $end
$var wire 2 5 clac_mode [1:0] $end
$var wire 16 6 opcode_a [15:0] $end
$var wire 16 7 opcode_b [15:0] $end
$var reg 1 : hwrite_r $end
$var reg 3 ; hsize_r [2:0] $end
$var reg 3 < hburst_r [2:0] $end
$var reg 2 = htrans_r [1:0] $end
$var reg 8 > haddr_r [7:0] $end
$var wire 1 ? ahb_write $end
$var wire 1 @ ahb_read $end
$var reg 1 A enable_r $end
$var reg 2 B ctrl_r [1:0] $end
$var reg 16 C opa_r [15:0] $end
$var reg 16 D opb_r [15:0] $end
$upscope $end


$scope module U_clac $end
$var wire 1 4 ctrl $end
$var wire 2 5 clac_mode [1:0] $end
$var wire 16 6 opcode_a [15:0] $end
$var wire 16 7 opcode_b [15:0] $end
$var reg 32 E result [31:0] $end
$upscope $end

$upscope $end

$upscope $end

$enddefinitions $end

#0
$dumpvars
0@
0?
04
0A
0!
0%
1+
0"
0#
0$
0:
b00000000000000000000000000000000 E
b00000000000000000000000000000000 9
bxxxxxxxxxxxxxxxxxxxxxxxxxxxxxxxx 1
bxxxxxxxxxxxxxxxxxxxxxxxxxxxxxxxx 2
bxxxxxxxxxxxxxxxxxxxxxxxxxxxxxxxx /
bxxxxxxxxxxxxxxxxxxxxxxxxxxxxxxxx 0
b00 5
b00 B
b00000000000000000000000000000000 *
b00000000 >
b000 '
b000 <
b00000000000000000000000000000000 -
b00 ,
b000 &
b000 ;
b00 (
b00 =
bxxxxxxxxxxxxxxxxxxxxxxxxxxxxxxxx )
b0000000000000000 C
b0000000000000000 D
b0000000000000000 6
b0000000000000000 7
bxxxxxxxxxxxxxxxxxxxxxxxxxxxxxxxx .
b00000000000000000000000000000000 8
b00000000 3
$end
#10000
1!
#20000
0!
#30000
1!
#40000
0!
#50000
1!
#60000
0!
#70000
1!
#80000
0!
#90000
1!
#100000
0!
#110000
1!
#120000
0!
#130000
1!
#140000
0!
#150000
1!
#160000
0!
#170000
1!
#180000
0!
#190000
1!
#200000
1"
0!
#210000
b00000000000000000000000000000100 /
b00000000000000000000000000000001 0
1!
#211000
b010 &
b10 (
1$
1#
1%
b00000000000000000000000000000100 *
b00000100 3
#220000
0!
#230000
1!
1:
b010 ;
b10 =
b00000100 >
1?
#231000
b000 &
b00 (
0$
0#
b00000000000000000000000000000001 )
#240000
0!
#250000
1!
b01 B
b01 5
0:
b000 ;
b00 =
0@
0?
#251000
b00000000000000000000000000000000 *
b00000000 3
#260000
0!
#270000
1!
#280000
0!
b00000000000000000000000000001000 /
b00000000000000000011001001010100 0
#290000
1!
#291000
b010 &
b10 (
1$
1#
b00000000000000000000000000001000 *
b00001000 3
#300000
0!
#310000
1!
1:
b010 ;
b10 =
b00001000 >
1?
#311000
b000 &
b00 (
0$
0#
b00000000000000000011001001010100 )
#320000
0!
#330000
1!
b0011001001010100 C
b0011001001010100 6
0:
b000 ;
b00 =
0@
0?
#331000
b00000000000000000000000000000000 *
b00000000 3
#340000
0!
#350000
1!
#360000
0!
b00000000000000000000000000001100 /
b00000000000000001111111111111111 0
#370000
1!
#371000
b010 &
b10 (
1$
1#
b00000000000000000000000000001100 *
b00001100 3
#380000
0!
#390000
1!
1:
b010 ;
b10 =
b00001100 >
1?
#391000
b000 &
b00 (
0$
0#
b00000000000000001111111111111111 )
#400000
0!
#410000
1!
b1111111111111111 D
b1111111111111111 7
0:
b000 ;
b00 =
0@
0?
#411000
b00000000000000000000000000000000 *
b00000000 3
#420000
0!
#430000
1!
#440000
0!
b00000000000000000000000000000000 /
b00000000000000000000000000000001 0
#450000
1!
#451000
b010 &
b10 (
1$
1#
#460000
0!
#470000
1!
1:
b010 ;
b10 =
b00000000 >
1?
#471000
b000 &
b00 (
0$
0#
b00000000000000000000000000000001 )
#480000
0!
#490000
1!
1A
14
0:
b000 ;
b00 =
b00000000000000001111111111111111 E
b00000000000000001111111111111111 8
0@
0?
#500000
0!
#510000
1!
#520000
0!
b00000000000000000000000000010000 1
#530000
1!
#531000
b00000000000000000000000000010000 *
b00010000 3
b010 &
b10 (
1#
#540000
0!
#550000
1!
b010 ;
b10 =
b00010000 >
1@
b00000000000000001111111111111111 9
b00000000000000001111111111111111 -
#551000
b000 &
b00 (
0#
#560000
0!
#570000
1!
b00000000000000001111111111111111 2
b00000000000000000000000000000000 *
b00000000 3
b000 ;
b00 =
0@
b00000000000000000000000000000000 9
b00000000000000000000000000000000 -
#580000
0!
#590000
1!
b00000000000000001111111111111111 .
